nornir_ansible/__init__.py
nornir_ansible/plugins/__init__.py
nornir_ansible/plugins/inventory/__init__.py
nornir_ansible/plugins/inventory/ansible.py
nornir_ansible-2023.12.28.dist-info/LICENSE
nornir_ansible-2023.12.28.dist-info/METADATA
nornir_ansible-2023.12.28.dist-info/WHEEL
nornir_ansible-2023.12.28.dist-info/entry_points.txt
nornir_ansible-2023.12.28.dist-info/top_level.txt
nornir_ansible-2023.12.28.dist-info/RECORD
