Metadata-Version: 2.1
Name: nornir-ansible
Version: 2023.12.28
Home-page: https://github.com/carlmontanari/nornir_ansible
Author: Carl Montanari
Author-email: carl.r.montanari@gmail.com
Classifier: Programming Language :: Python :: 3
Classifier: Programming Language :: Python :: 3.8
Classifier: Programming Language :: Python :: 3.9
Classifier: Programming Language :: Python :: 3.10
Requires-Python: >=3.8
License-File: LICENSE
Requires-Dist: ruamel.yaml <1.0.0,>=0.16.10
Requires-Dist: nornir <4.0.0,>=3.4.0
